{
    "title": "Vapor Blue",
    "description": "A mix of light and dark apps with a blue accent color",
    "author": "Josh Rhame",
    "link": "https://play.google.com/store/apps/details?id=vaporblue.rhamej&hl=en",
    "backup_link": "false",
    "icon": "http://i.imgur.com/Kbj2LMe.png",
    "promo": "http://i.imgur.com/1SPsAZZ.png",
    "screenshot_1": "http://i.imgur.com/LEPV0Iv.png",
    "screenshot_2": "http://i.imgur.com/3zaOvT5.png",
    "screenshot_3": "http://i.imgur.com/rJVmCO2.png",
    "googleplus": "https://plus.google.com/u/0/communities/113011005082687367133",
    "version": "2.8",
    "donate_link": "false",
    "donate_version": "false",
    "bootani": "false",
    "font": "false",
    "wallpaper": "false",
    "plugin_version": "false",
    "for_L": "true",
    "for_M": "false",
    "basic": "false",
    "basic_m": "false",
    "type2": "true",
    "type3": "false",
    "type3_m": "false",
    "touchwiz": "false",
    "lg": "false",
    "sense": "false",
    "xperia": "false",
    "zenui": "false",
    "hdpi": "true",
    "mdpi": "false",
    "xhdpi": "true",
    "xxhdpi": "true",
    "xxxhdpi": "true",
    "free": "false",
    "donate": "false",
    "paid": "true",
    "needs_update": "false",
    "will_update": "true",
    "iconpack": "false"
}